tongyi/__init__.py
tongyi/_tongyi.py
tongyi-0.0.1a1.dist-info/METADATA
tongyi-0.0.1a1.dist-info/WHEEL
tongyi-0.0.1a1.dist-info/top_level.txt
tongyi-0.0.1a1.dist-info/RECORD
