Metadata-Version: 2.1
Name: tongyi
Version: 0.0.1a1
Summary: test for mutiple platforms
Author: dicey
Author-email: dicey.dai@clickcorp.com
Classifier: Programming Language :: Python :: 3.7
Classifier: Programming Language :: Python :: 3.8
Classifier: Programming Language :: Python :: 3.9
Classifier: Programming Language :: Python :: 3.10
Classifier: License :: OSI Approved :: Apache Software License
Classifier: Operating System :: OS Independent
